{
    "header_text": "Spilled Coffee: Write Some Thoughts",
    "header_icon": "assets/subtitle.png",
    "elements": [
        {
            "type": "Text",
            "text": "You're on a date at a coffee shop with a person you really like. As you walk back to the table, you trip and fall and spill coffee everywhere.\n\nPlease take 30 seconds to write different thoughts. The next button will appear automatically. \n\nThoughts in the moment:"
        },
        {
            "type": "Entry"
        }
    ],
    "navigation_conditions": [
        {
            "wait_for_time": 30000
        },
        "wait_for_click"
    ]
}