{
    "header_text": "You are a dog owner. You've had difficulty with your balance lately, and you worry that it will become harder to take your dog for a walk. Thinking about whether you will be able to continue to care for your dog makes you feel overwhelmed.",
    "header_icon": "assets/subtitle.png",
    "elements": [
        {
            "type": "Text",
            "Text": "Your dog will be..."
        },
        {
            "type": "Buttons",
            "name": "You are a dog owner. You've had difficulty with your balance lately, and you worry that it will become harder to take your dog for a walk. Thinking about whether you will be able to continue to care for your dog makes you feel overwhelmed._Early/Mid-Stage Symptoms_comp_question",
            "correct_feedback": "Correct!",
            "incorrect_feedback": "Whoops! That doesn't look right. Please wait a moment and try again.",
            "incorrect_delay": 5000,
            "buttons": [
                "Cared for",
                "Neglected"
            ],
            "columnCount": 1,
            "correct_value": "Cared for"
        }
    ],
    "navigation_conditions": [
        "wait_for_correct",
        "wait_for_click"
    ]
}