{
    "header_text": "You are giving a speech at your cousin's graduation party. During the toast, you struggle to remember the exact words you wanted to say, and you notice two people beginning to whisper in the corner. You think they are probably talking about your cousin.",
    "header_icon": "assets/subtitle.png",
    "elements": [
        {
            "type": "Text",
            "Text": "During the toast, people start talking about your..."
        },
        {
            "type": "Buttons",
            "name": "You are giving a speech at your cousin's graduation party. During the toast, you struggle to remember the exact words you wanted to say, and you notice two people beginning to whisper in the corner. You think they are probably talking about your cousin._Family & Home Life_comp_question",
            "correct_feedback": "Correct!",
            "incorrect_feedback": "Whoops! That doesn't look right. Please wait a moment and try again.",
            "incorrect_delay": 5000,
            "buttons": [
                "Quiet voice",
                "Nephew"
            ],
            "columnCount": 1,
            "correct_value": "Nephew"
        }
    ],
    "navigation_conditions": [
        "wait_for_correct",
        "wait_for_click"
    ]
}