{
    "header_text": "You are single and pretty content with it. One day, your friends start pressuring you and telling you that you are running out of time to meet someone. You tell yourself that as long as you are happy, there's no need to rush.",
    "header_icon": "assets/subtitle.png",
    "elements": [
        {
            "type": "Label",
            "text": "You are single and pretty content with it. One day, your friends start pressuring you and telling you that you are running out of time to meet someone. You tell yourself that as long as you are happy, there's no need to rush."
        },
        {
            "type": "Media",
            "url": "./images/555.jpg"
        }
    ]
}