{
    "header_text": "Your child really wants to go to a theme park for vacation this year. You've been researching the cost of the trip, and you don't think you can afford it. You think that you can find an alternative trip that your child will still enjoy. ",
    "header_icon": "assets/subtitle.png",
    "elements": [
        {
            "type": "Text",
            "Text": "Can you make it to a theme park this year?"
        },
        {
            "type": "Buttons",
            "name": "Your child really wants to go to a theme park for vacation this year. You've been researching the cost of the trip, and you don't think you can afford it. You think that you can find an alternative trip that your child will still enjoy. _Finances_comp_question",
            "correct_feedback": "Correct!",
            "incorrect_feedback": "Whoops! That doesn't look right. Please wait a moment and try again.",
            "incorrect_delay": 5000,
            "buttons": [
                "Yes",
                "No"
            ],
            "columnCount": 1,
            "correct_value": "No"
        }
    ],
    "navigation_conditions": [
        "wait_for_correct",
        "wait_for_click"
    ]
}