{
    "header_text": "You have been invited to a gala for your partner's work. While dancing, you feel unsteady and start to fall, but your partner catches you in time. Regardless, you feel embarrassed. ",
    "header_icon": "assets/subtitle.png",
    "elements": [
        {
            "type": "Label",
            "text": "You have been invited to a gala for your partner's work. While dancing, you feel unsteady and start to fall, but your partner catches you in time. Regardless, you feel embarrassed. "
        },
        {
            "type": "Media",
            "url": "./images/578.jpg"
        }
    ]
}