{
    "header_text": "Your car is broken again, and you have to walk a few blocks to get to where you need to go. You feel your chest tighten, and you feel out of breath as you reach your destination. You feel invigorated.",
    "header_icon": "assets/subtitle.png",
    "elements": [
        {
            "type": "Label",
            "text": "Your car is broken again, and you have to walk a few blocks to get to where you need to go. You feel your chest tighten, and you feel out of breath as you reach your destination. You feel invigorated."
        },
        {
            "type": "Media",
            "url": "./images/475.jpg"
        }
    ]
}