{
    "header_text": "At your routine doctor's appointment, your doctor decides to run a few tests to evaluate your health. They tell you that they will have your results within a week. While you wait for your results, you think you are likely healthy.",
    "header_icon": "assets/subtitle.png",
    "elements": [
        {
            "type": "Label",
            "text": "At your routine doctor's appointment, your doctor decides to run a few tests to evaluate your health. They tell you that they will have your results within a week. While you wait for your results, you think you are likely healthy."
        },
        {
            "type": "Media",
            "url": "./images/438.jpg"
        }
    ]
}