{
    "header_text": "You are catching up with a group of friends you haven't seen in a while. In the middle of telling a story, you lose track of what you intended to say and worry about your friends' reactions. You tell your friends that you lost your train of thought, and they are understanding. ",
    "header_icon": "assets/subtitle.png",
    "elements": [
        {
            "type": "Text",
            "Text": "When you talk, your friends are..."
        },
        {
            "type": "Buttons",
            "name": "You are catching up with a group of friends you haven't seen in a while. In the middle of telling a story, you lose track of what you intended to say and worry about your friends' reactions. You tell your friends that you lost your train of thought, and they are understanding. _Early/Mid-Stage Symptoms_comp_question",
            "correct_feedback": "Correct!",
            "incorrect_feedback": "Whoops! That doesn't look right. Please wait a moment and try again.",
            "incorrect_delay": 5000,
            "buttons": [
                "Engaged",
                "Confused"
            ],
            "columnCount": 1,
            "correct_value": "Engaged"
        }
    ],
    "navigation_conditions": [
        "wait_for_correct",
        "wait_for_click"
    ]
}