{
    "header_text": "Feedback on your work",
    "header_icon": "assets/subtitle.png",
    "elements": [
        {
            "type": "Text",
            "Text": "Your boss probably thinks that..."
        },
        {
            "type": "Buttons",
            "name": "Feedback on your work_Work/Career Development_comp_question",
            "correct_feedback": "Correct!",
            "incorrect_feedback": "Whoops! That doesn't look right. Please wait a moment and try again.",
            "incorrect_delay": 5000,
            "buttons": [
                "You are incapable",
                "You have great potential"
            ],
            "column_count": 1,
            "correct_value": "You have great potential"
        }
    ],
    "navigation_conditions": [
        "wait_for_correct",
        "wait_for_click"
    ],
    "type": "resilience/negation",
    "scenario_num": 5
}