{
    "header_text": "You've been very busy the past few months, and you haven't had a lot of free time. You finally have a chance to rest, but you feel guilty that you're taking a break rather than completing work. You think that you deserve to relax. ",
    "header_icon": "assets/subtitle.png",
    "elements": [
        {
            "type": "Label",
            "text": "You've been very busy the past few months, and you haven't had a lot of free time. You finally have a chance to rest, but you feel guilty that you're taking a break rather than completing work. You think that you deserve to relax. "
        },
        {
            "type": "Media",
            "url": "./images/85.jpg"
        }
    ]
}