{
    "header_text": "Your home is a mess, and you decide to tackle some chores. You start to fold the laundry, but you find that you're struggling to fold clothes neatly. At first this causes you to feel overwhelmed, but you remind yourself to take a deep breath and relax.",
    "header_icon": "assets/subtitle.png",
    "elements": [
        {
            "type": "Label",
            "text": "Your home is a mess, and you decide to tackle some chores. You start to fold the laundry, but you find that you're struggling to fold clothes neatly. At first this causes you to feel overwhelmed, but you remind yourself to take a deep breath and relax."
        },
        {
            "type": "Media",
            "url": "./images/212.jpg"
        }
    ]
}