{
    "header_text": "Thinking fast at work",
    "header_icon": "assets/subtitle.png",
    "elements": [
        {
            "type": "Text",
            "text": "You are at your workplace, and a colleague asks you to perform a task that you have completed countless times before. Today, you struggle to recall the steps needed to complete the task, and your colleague starts to look concerned. Regardless of what they think, you do not question your own..."
        },
        {
            "type": "Entry"
        }
    ],
    "navigation_conditions": "wait_for_correct",
    "type": "positive",
    "scenario_num": 8
}